{
    "subject name": "Qualitative Methods for Evaluation",
    "subject code": "EDUC90716",
    "subject availability": [
        "Term 3 - Online"
    ],
    "overview": [
        "This subject provides students with an introduction to the theory and application of qualitative inquiry. Topics that will be examined include: orientations to, and debates surrounding, qualitative approaches; the collection, display and analysis of qualitative data; the use of systematic methods of data reduction, display and analysis and how qualitative research methods are commonly used in evaluation studies."
    ],
    "aims": [],
    "indicative content": [],
    "intended learning outcomes": [
        "define qualitative inquiry and relate it to its theoretical and philosophical foundations",
        "determine the conditions and questions for which a qualitative study is most appropriate",
        "design and conduct a qualitative study including: selecting and applying a range of data collection techniques; creating and analysing data from field notes and interview transcriptions; developing coding categories and presenting results."
    ],
    "pre-requisites": [
        {
            "option": "Option 1",
            "necessary pre-requisite": [],
            "one of pre-requisite": [],
            "additional pre-requisite": [
                "None"
            ]
        }
    ],
    "corequisites": "None",
    "non-allowed subjects": [
        "EDUC90795"
    ],
    "assessments": [
        {
            "description": "Quizzes (2 checks for understanding). 250 words (each)",
            "timing": "Week 2 and Week 8",
            "percentage": "10%"
        },
        {
            "description": "Application assignments (divided among 5 practical applications). 3000 words (total)",
            "timing": "From Week 2 to Week 7",
            "percentage": "50%"
        },
        {
            "description": "Written report based on qualitative data analysis and interpretation. 1500 words",
            "timing": "Week 9",
            "percentage": "40%"
        }
    ],
    "dates and times": [
        {
            "Term 3 - Online": [
                {
                    "Coordinator": "Sue Mentha"
                },
                {
                    "Mode of delivery": "Online"
                },
                {
                    "Contact hours": "24 hours"
                },
                {
                    "Total time commitment": "170 hours"
                },
                {
                    "Pre teaching start date": "15 July 2024"
                },
                {
                    "Pre teaching requirements": "During the pre-teaching period, students should familiarise themselves with the online platform and may like to take the opportunity to read through preliminary information about the subject and the services and support that is available to them. Students are encouraged to use this time to also introduce themselves to peers and teaching staff and to learn about those they will be studying with throughout the term."
                },
                {
                    "Teaching period": "22 July 2024 to 15 September 2024"
                },
                {
                    "Last self-enrol date": "16 July 2024"
                },
                {
                    "Census date": "9 August 2024"
                },
                {
                    "Last date to withdraw without fail": "30 August 2024"
                },
                {
                    "Assessment period ends": "22 September 2024"
                }
            ]
        }
    ],
    "contact information": [
        {
            "Term 3": {
                "name": [
                    "Admission and enrolment:"
                ],
                "email": [
                    "continuing-education@unimelb.edu.au",
                    "https://unimelb.edu.au/professional-development/contact-us"
                ]
            }
        }
    ],
    "further info": {
        "Texts": [
            {
                "Prescribed texts": [
                    "Willis, J.W. (2007). Foundations of qualitative research: Interpretive and critical approaches. Thousand Oaks: SAGE Publications, Inc. Retrieved from DOI:http://dx.doi.org/10.4135/9781452230108",
                    "Available in print and online:",
                    "Print ISBN: 9781412927413",
                    "Online ISBN: 9781452230108"
                ]
            }
        ],
        "Related Handbook entries": [
            "This subject contributes to the following:"
        ],
        "Available through the Community Access Program": [
            {
                "About the Community Access Program (CAP)": [
                    "This subject is available through theCommunity Access Program(also called Single Subject Studies) which allows you to enrol in single subjects offered by the University of Melbourne, without the commitment required to complete a whole degree.",
                    "Entry requirements including prerequisites may apply. Please refer to theCAP applications pagefor further information."
                ]
            }
        ],
        "Available to Study Abroad and/or Study Exchange Students": [
            "This subject is available to students studying at the University from eligible overseas institutions on exchange and study abroad. Students are required to satisfy any listed requirements, such as pre- and co-requisites, for enrolment in the subject."
        ]
    }
}