{
    "subject name": "Societal Implications of Genomics",
    "subject code": "POPH90226",
    "subject availability": [
        "Semester 1"
    ],
    "overview": [
        "This subject will examine the ethical, legal and social implications (ELSI) of genetics and genomics. It will be organised into 3 overarching topics:",
        "The principles of ethical and legal frameworks will be introduced, and will be applied in the context of genomics in healthcare practice, with consideration of professional and personal values.",
        "The foundations of public health will be introduced and applied to public health genomics programs, particularly genetic screening.",
        "Personal genomic testing will be discussed from multiple perspectives, including historical, ethical, regulatory and social.  How genetics is communicated and genetic literacy in the community will be explored."
    ],
    "aims": [],
    "indicative content": [],
    "pre-requisites": [
        {
            "option": "Option 1",
            "necessary pre-requisite": [],
            "one of pre-requisite": [],
            "additional pre-requisite": [
                "None"
            ]
        }
    ],
    "corequisites": "None",
    "non-allowed subjects": "None",
    "assessments": [
        {
            "description": "Online quiz. 30 minutes",
            "timing": "First half of the semester",
            "percentage": "10%"
        },
        {
            "description": "Written task. 1500 words",
            "timing": "First half of the semester",
            "percentage": "30%"
        },
        {
            "description": "Online Quiz. 15 minutes",
            "timing": "Mid semester",
            "percentage": "5%"
        },
        {
            "description": "Written task. 1500 words",
            "timing": "Mid semester",
            "percentage": "30%"
        },
        {
            "description": "Online quiz. 15 minutes",
            "timing": "End of semester",
            "percentage": "5%"
        },
        {
            "description": "Practical communication task. 1000 words (equivalent)",
            "timing": "End of semester",
            "percentage": "20%"
        }
    ],
    "dates and times": [
        {
            "Semester 1": [
                {
                    "Principal coordinators": "Gabrielle Reid Vogl and Linda Cicciarelli Riddington"
                },
                {
                    "Mode of delivery": "On Campus (Parkville)"
                },
                {
                    "Contact hours": ""
                },
                {
                    "Total time commitment": "170 hours"
                },
                {
                    "Teaching period": "26 February 2024 to 26 May 2024"
                },
                {
                    "Last self-enrol date": "8 March 2024"
                },
                {
                    "Census date": "3 April 2024"
                },
                {
                    "Last date to withdraw without fail": "3 May 2024"
                },
                {
                    "Assessment period ends": "21 June 2024"
                }
            ]
        }
    ],
    "contact information": [],
    "further info": {
        "Texts": [
            {
                "Prescribed texts": [
                    "No prescribed text"
                ]
            }
        ],
        "Related Handbook entries": [
            "This subject contributes to the following:"
        ],
        "Available to Study Abroad and/or Study Exchange Students": [
            "This subject is available to students studying at the University from eligible overseas institutions on exchange and study abroad. Students are required to satisfy any listed requirements, such as pre- and co-requisites, for enrolment in the subject."
        ]
    }
}